{
    "dailySummary": [
        {
            "day": "2025-10-01",
            "MeanTemp": 20.6,
            "highTemp": 25.2,
            "MinTemp": 17.7,
            "Rain": 0,
            "AvgWind": 5,
            "HighWind": 29,
            "highTempTime": "14:20",
            "lowTempTime": "6:40",
            "HighWindTime": "13:50",
            "DomDir": "WNW"
        },
        {
            "day": "2025-10-02",
            "MeanTemp": 22.3,
            "highTemp": 27.7,
            "MinTemp": 17.4,
            "Rain": 0,
            "AvgWind": 1,
            "HighWind": 21,
            "highTempTime": "15:40",
            "lowTempTime": "6:50",
            "HighWindTime": "12:40",
            "DomDir": "N"
        },
        {
            "day": "2025-10-03",
            "MeanTemp": 25.3,
            "highTemp": 31.4,
            "MinTemp": 19.3,
            "Rain": 0,
            "AvgWind": 1,
            "HighWind": 26,
            "highTempTime": "15:40",
            "lowTempTime": "3:50",
            "HighWindTime": "13:30",
            "DomDir": "SE"
        },
        {
            "day": "2025-10-04",
            "MeanTemp": 23.7,
            "highTemp": 30.9,
            "MinTemp": 19.9,
            "Rain": 0,
            "AvgWind": 2,
            "HighWind": 27,
            "highTempTime": "14:40",
            "lowTempTime": "23:40",
            "HighWindTime": "20:20",
            "DomDir": "NNW"
        },
        {
            "day": "2025-10-05",
            "MeanTemp": 21.7,
            "highTemp": 27.5,
            "MinTemp": 19.1,
            "Rain": 0,
            "AvgWind": 5,
            "HighWind": 34,
            "highTempTime": "14:40",
            "lowTempTime": "5:10",
            "HighWindTime": "17:40",
            "DomDir": "N"
        },
        {
            "day": "2025-10-06",
            "MeanTemp": 20.2,
            "highTemp": 24.6,
            "MinTemp": 17.9,
            "Rain": 0,
            "AvgWind": 4,
            "HighWind": 27,
            "highTempTime": "15:40",
            "lowTempTime": "6:30",
            "HighWindTime": "18:20",
            "DomDir": "NNW"
        },
        {
            "day": "2025-10-07",
            "MeanTemp": 21,
            "highTemp": 25.8,
            "MinTemp": 16.8,
            "Rain": 0,
            "AvgWind": 2,
            "HighWind": 26,
            "highTempTime": "13:30",
            "lowTempTime": "4:50",
            "HighWindTime": "17:30",
            "DomDir": "NNW"
        },
        {
            "day": "2025-10-08",
            "MeanTemp": 21.9,
            "highTemp": 27.2,
            "MinTemp": 15.8,
            "Rain": 0,
            "AvgWind": 2,
            "HighWind": 34,
            "highTempTime": "14:40",
            "lowTempTime": "6:10",
            "HighWindTime": "17:10",
            "DomDir": "W"
        },
        {
            "day": "2025-10-09",
            "MeanTemp": 19.9,
            "highTemp": 22.8,
            "MinTemp": 17.5,
            "Rain": 0,
            "AvgWind": 4,
            "HighWind": 37,
            "highTempTime": "13:0",
            "lowTempTime": "23:10",
            "HighWindTime": "9:20",
            "DomDir": "NW"
        },
        {
            "day": "2025-10-10",
            "MeanTemp": 19,
            "highTemp": 23.9,
            "MinTemp": 15.8,
            "Rain": 0,
            "AvgWind": 1,
            "HighWind": 23,
            "highTempTime": "16:10",
            "lowTempTime": "7:0",
            "HighWindTime": "16:10",
            "DomDir": "N"
        },
        {
            "day": "2025-10-11",
            "MeanTemp": 20.2,
            "highTemp": 27.7,
            "MinTemp": 15.2,
            "Rain": 0,
            "AvgWind": 2,
            "HighWind": 24,
            "highTempTime": "14:10",
            "lowTempTime": "5:30",
            "HighWindTime": "16:40",
            "DomDir": "NNW"
        },
        {
            "day": "2025-10-12",
            "MeanTemp": 18.7,
            "highTemp": 22.2,
            "MinTemp": 16.8,
            "Rain": 0,
            "AvgWind": 4,
            "HighWind": 34,
            "highTempTime": "14:40",
            "lowTempTime": "4:10",
            "HighWindTime": "16:50",
            "DomDir": "NW"
        },
        {
            "day": "2025-10-13",
            "MeanTemp": 19.3,
            "highTemp": 24.9,
            "MinTemp": 15.1,
            "Rain": 0,
            "AvgWind": 1,
            "HighWind": 19,
            "highTempTime": "15:50",
            "lowTempTime": "7:0",
            "HighWindTime": "16:40",
            "DomDir": "W"
        },
        {
            "day": "2025-10-14",
            "MeanTemp": 18.6,
            "highTemp": 24.6,
            "MinTemp": 14.2,
            "Rain": 0,
            "AvgWind": 1,
            "HighWind": 24,
            "highTempTime": "14:40",
            "lowTempTime": "6:40",
            "HighWindTime": "17:30",
            "DomDir": "NNW"
        },
        {
            "day": "2025-10-15",
            "MeanTemp": 18.7,
            "highTemp": 24.6,
            "MinTemp": 13.8,
            "Rain": 0,
            "AvgWind": 1,
            "HighWind": 19,
            "highTempTime": "16:30",
            "lowTempTime": "7:10",
            "HighWindTime": "18:20",
            "DomDir": "N"
        },
        {
            "day": "2025-10-16",
            "MeanTemp": 19.7,
            "highTemp": 26.2,
            "MinTemp": 15.2,
            "Rain": 0,
            "AvgWind": 1,
            "HighWind": 23,
            "highTempTime": "15:0",
            "lowTempTime": "6:10",
            "HighWindTime": "16:40",
            "DomDir": "NNW"
        },
        {
            "day": "2025-10-17",
            "MeanTemp": 20.5,
            "highTemp": 27.7,
            "MinTemp": 16.4,
            "Rain": 0,
            "AvgWind": 1,
            "HighWind": 21,
            "highTempTime": "14:20",
            "lowTempTime": "6:50",
            "HighWindTime": "23:0",
            "DomDir": "NW"
        },
        {
            "day": "2025-10-18",
            "MeanTemp": 19.4,
            "highTemp": 24.4,
            "MinTemp": 16.3,
            "Rain": 0,
            "AvgWind": 1,
            "HighWind": 24,
            "highTempTime": "14:40",
            "lowTempTime": "23:40",
            "HighWindTime": "14:20",
            "DomDir": "NW"
        },
        {
            "day": "2025-10-19",
            "MeanTemp": 18.5,
            "highTemp": 23.3,
            "MinTemp": 15.7,
            "Rain": 0,
            "AvgWind": 2,
            "HighWind": 29,
            "highTempTime": "13:20",
            "lowTempTime": "5:20",
            "HighWindTime": "15:10",
            "DomDir": "NNW"
        },
        {
            "day": "2025-10-20",
            "MeanTemp": 20.4,
            "highTemp": 26.3,
            "MinTemp": 16.6,
            "Rain": 0,
            "AvgWind": 1,
            "HighWind": 23,
            "highTempTime": "13:40",
            "lowTempTime": "6:30",
            "HighWindTime": "14:10",
            "DomDir": "NNW"
        },
        {
            "day": "2025-10-21",
            "MeanTemp": 22.3,
            "highTemp": 27.8,
            "MinTemp": 16.9,
            "Rain": 0,
            "AvgWind": 0,
            "HighWind": 14,
            "highTempTime": "14:0",
            "lowTempTime": "7:0",
            "HighWindTime": "14:40",
            "DomDir": "NNE"
        },
        {
            "day": "2025-10-22",
            "MeanTemp": 23.4,
            "highTemp": 28.7,
            "MinTemp": 18.5,
            "Rain": 0,
            "AvgWind": 0,
            "HighWind": 13,
            "highTempTime": "15:30",
            "lowTempTime": "1:30",
            "HighWindTime": "10:30",
            "DomDir": "ESE"
        },
        {
            "day": "2025-10-23",
            "MeanTemp": 24.4,
            "highTemp": 31.6,
            "MinTemp": 19.6,
            "Rain": 0,
            "AvgWind": 0,
            "HighWind": 21,
            "highTempTime": "14:40",
            "lowTempTime": "7:0",
            "HighWindTime": "14:0",
            "DomDir": "SE"
        },
        {
            "day": "2025-10-24",
            "MeanTemp": 21.3,
            "highTemp": 25.8,
            "MinTemp": 16.9,
            "Rain": 0,
            "AvgWind": 2,
            "HighWind": 24,
            "highTempTime": "13:50",
            "lowTempTime": "23:50",
            "HighWindTime": "14:20",
            "DomDir": "NW"
        },
        {
            "day": "2025-10-25",
            "MeanTemp": 19.9,
            "highTemp": 26.9,
            "MinTemp": 13.9,
            "Rain": 0,
            "AvgWind": 1,
            "HighWind": 21,
            "highTempTime": "15:30",
            "lowTempTime": "2:0",
            "HighWindTime": "17:20",
            "DomDir": "N"
        },
        {
            "day": "2025-10-26",
            "MeanTemp": 20,
            "highTemp": 26.4,
            "MinTemp": 15.7,
            "Rain": 0,
            "AvgWind": 1,
            "HighWind": 29,
            "highTempTime": "12:30",
            "lowTempTime": "3:0",
            "HighWindTime": "14:10",
            "DomDir": "NW"
        },
        {
            "day": "2025-10-27",
            "MeanTemp": 20.3,
            "highTemp": 26.9,
            "MinTemp": 14.7,
            "Rain": 0,
            "AvgWind": 0,
            "HighWind": 16,
            "highTempTime": "15:20",
            "lowTempTime": "4:0",
            "HighWindTime": "15:50",
            "DomDir": "NW"
        },
        {
            "day": "2025-10-28",
            "MeanTemp": 20.3,
            "highTemp": 27.4,
            "MinTemp": 15.8,
            "Rain": 0,
            "AvgWind": 0,
            "HighWind": 19,
            "highTempTime": "11:30",
            "lowTempTime": "5:50",
            "HighWindTime": "23:20",
            "DomDir": "NNW"
        },
        {
            "day": "2025-10-29",
            "MeanTemp": 19,
            "highTemp": 24.1,
            "MinTemp": 15.1,
            "Rain": 0,
            "AvgWind": 3,
            "HighWind": 26,
            "highTempTime": "13:20",
            "lowTempTime": "5:40",
            "HighWindTime": "14:0",
            "DomDir": "NW"
        },
        {
            "day": "2025-10-30",
            "MeanTemp": 21,
            "highTemp": 25.8,
            "MinTemp": 15.3,
            "Rain": 0,
            "AvgWind": 0,
            "HighWind": 24,
            "highTempTime": "15:10",
            "lowTempTime": "6:0",
            "HighWindTime": "10:20",
            "DomDir": "ESE"
        },
        {
            "day": "2025-10-31",
            "MeanTemp": 22.8,
            "highTemp": 27,
            "MinTemp": 19.3,
            "Rain": 0,
            "AvgWind": 0,
            "HighWind": 21,
            "highTempTime": "14:50",
            "lowTempTime": "4:0",
            "HighWindTime": "11:40",
            "DomDir": "ESE"
        }
    ],
    "monthSummary": [
        {
            "MeanTemp": 20.8,
            "highTemp": 31.6,
            "MinTemp": 13.8,
            "AvgWind": 2,
            "HighWind": 37,
            "DomDir": "NNW",
            "highTempDate": "2025-10-23",
            "lowTempDate": "2025-10-15",
            "rain": 0
        }
    ],
    "rainSummary": {
        "daysOfrain": {
            "rdays": 0
        },
        "daysOfrain2": {
            "rdays": 0
        },
        "daysOfrain20": {
            "rdays": 0
        }
    }
}